{"nodes": [{"id": "c_users_ash_documents_resume_ats_resume_tailor_models_resume_schema_py", "label": "resume_schema.py", "file_type": "code", "source_file": "C:\\Users\\ash\\Documents\\resume-ats\\resume_tailor\\models\\resume_schema.py", "source_location": "L1"}, {"id": "models_resume_schema_contact", "label": "Contact", "file_type": "code", "source_file": "C:\\Users\\ash\\Documents\\resume-ats\\resume_tailor\\models\\resume_schema.py", "source_location": "L4"}, {"id": "basemodel", "label": "BaseModel", "file_type": "code", "source_file": "", "source_location": ""}, {"id": "models_resume_schema_experience", "label": "Experience", "file_type": "code", "source_file": "C:\\Users\\ash\\Documents\\resume-ats\\resume_tailor\\models\\resume_schema.py", "source_location": "L12"}, {"id": "models_resume_schema_education", "label": "Education", "file_type": "code", "source_file": "C:\\Users\\ash\\Documents\\resume-ats\\resume_tailor\\models\\resume_schema.py", "source_location": "L19"}, {"id": "models_resume_schema_project", "label": "Project", "file_type": "code", "source_file": "C:\\Users\\ash\\Documents\\resume-ats\\resume_tailor\\models\\resume_schema.py", "source_location": "L27"}, {"id": "models_resume_schema_resume", "label": "Resume", "file_type": "code", "source_file": "C:\\Users\\ash\\Documents\\resume-ats\\resume_tailor\\models\\resume_schema.py", "source_location": "L32"}], "edges": [{"source": "c_users_ash_documents_resume_ats_resume_tailor_models_resume_schema_py", "target": "pydantic", "relation": "imports_from", "context": "import", "confidence": "EXTRACTED", "source_file": "C:\\Users\\ash\\Documents\\resume-ats\\resume_tailor\\models\\resume_schema.py", "source_location": "L1", "weight": 1.0}, {"source": "c_users_ash_documents_resume_ats_resume_tailor_models_resume_schema_py", "target": "typing", "relation": "imports_from", "context": "import", "confidence": "EXTRACTED", "source_file": "C:\\Users\\ash\\Documents\\resume-ats\\resume_tailor\\models\\resume_schema.py", "source_location": "L2", "weight": 1.0}, {"source": "c_users_ash_documents_resume_ats_resume_tailor_models_resume_schema_py", "target": "models_resume_schema_contact", "relation": "contains", "confidence": "EXTRACTED", "source_file": "C:\\Users\\ash\\Documents\\resume-ats\\resume_tailor\\models\\resume_schema.py", "source_location": "L4", "weight": 1.0}, {"source": "models_resume_schema_contact", "target": "basemodel", "relation": "inherits", "confidence": "EXTRACTED", "source_file": "C:\\Users\\ash\\Documents\\resume-ats\\resume_tailor\\models\\resume_schema.py", "source_location": "L4", "weight": 1.0}, {"source": "c_users_ash_documents_resume_ats_resume_tailor_models_resume_schema_py", "target": "models_resume_schema_experience", "relation": "contains", "confidence": "EXTRACTED", "source_file": "C:\\Users\\ash\\Documents\\resume-ats\\resume_tailor\\models\\resume_schema.py", "source_location": "L12", "weight": 1.0}, {"source": "models_resume_schema_experience", "target": "basemodel", "relation": "inherits", "confidence": "EXTRACTED", "source_file": "C:\\Users\\ash\\Documents\\resume-ats\\resume_tailor\\models\\resume_schema.py", "source_location": "L12", "weight": 1.0}, {"source": "c_users_ash_documents_resume_ats_resume_tailor_models_resume_schema_py", "target": "models_resume_schema_education", "relation": "contains", "confidence": "EXTRACTED", "source_file": "C:\\Users\\ash\\Documents\\resume-ats\\resume_tailor\\models\\resume_schema.py", "source_location": "L19", "weight": 1.0}, {"source": "models_resume_schema_education", "target": "basemodel", "relation": "inherits", "confidence": "EXTRACTED", "source_file": "C:\\Users\\ash\\Documents\\resume-ats\\resume_tailor\\models\\resume_schema.py", "source_location": "L19", "weight": 1.0}, {"source": "c_users_ash_documents_resume_ats_resume_tailor_models_resume_schema_py", "target": "models_resume_schema_project", "relation": "contains", "confidence": "EXTRACTED", "source_file": "C:\\Users\\ash\\Documents\\resume-ats\\resume_tailor\\models\\resume_schema.py", "source_location": "L27", "weight": 1.0}, {"source": "models_resume_schema_project", "target": "basemodel", "relation": "inherits", "confidence": "EXTRACTED", "source_file": "C:\\Users\\ash\\Documents\\resume-ats\\resume_tailor\\models\\resume_schema.py", "source_location": "L27", "weight": 1.0}, {"source": "c_users_ash_documents_resume_ats_resume_tailor_models_resume_schema_py", "target": "models_resume_schema_resume", "relation": "contains", "confidence": "EXTRACTED", "source_file": "C:\\Users\\ash\\Documents\\resume-ats\\resume_tailor\\models\\resume_schema.py", "source_location": "L32", "weight": 1.0}, {"source": "models_resume_schema_resume", "target": "basemodel", "relation": "inherits", "confidence": "EXTRACTED", "source_file": "C:\\Users\\ash\\Documents\\resume-ats\\resume_tailor\\models\\resume_schema.py", "source_location": "L32", "weight": 1.0}], "raw_calls": []}